{
  "$schema": "https://frontmatter.codes/frontmatter.schema.json",
  "frontMatter.framework.id": "astro",
  "frontMatter.preview.host": "http://localhost:4321",
  "frontMatter.content.publicFolder": "public",
  "frontMatter.content.pageFolders": [
    {
      "title": "blog",
      "path": "[[workspace]]/src/content/blog"
    }
  ],
  "frontMatter.taxonomy.contentTypes": [
    {
      "name": "blog",
      "pageBundle": false,
      "previewPath": "'blog'",
      "filePrefix": null,
      "clearEmpty": true,
      "fields": [
        {
          "title": "title",
          "name": "title",
          "type": "string"
        },
        {
          "title": "pubDate",
          "name": "pubDate",
          "type": "datetime"
        },
        {
          "title": "type",
          "name": "type",
          "type": "string"
        },
        {
          "title": "description",
          "name": "description",
          "type": "string"
        },
        {
          "title": "heroImage",
          "name": "heroImage",
          "type": "image"
        },
        {
          "title": "keywords",
          "name": "keywords",
          "type": "choice",
          "choices": ["javascript", "validation"]
        },
        {
          "title": "categories",
          "name": "categories",
          "type": "categories"
        },
        {
          "title": "tags",
          "name": "tags",
          "type": "tags"
        }
      ]
    }
  ]
}
